graphdict/__init__.py
graphdict/conftest.py
graphdict/convert.py
graphdict/convert_matrix.py
graphdict/exception.py
graphdict/relabel.py
graphdict/algorithms/__init__.py
graphdict/algorithms/asteroidal.py
graphdict/algorithms/boundary.py
graphdict/algorithms/bridges.py
graphdict/algorithms/chains.py
graphdict/algorithms/chordal.py
graphdict/algorithms/clique.py
graphdict/algorithms/cluster.py
graphdict/algorithms/communicability_alg.py
graphdict/algorithms/core.py
graphdict/algorithms/covering.py
graphdict/algorithms/cuts.py
graphdict/algorithms/cycles.py
graphdict/algorithms/d_separation.py
graphdict/algorithms/dag.py
graphdict/algorithms/distance_measures.py
graphdict/algorithms/distance_regular.py
graphdict/algorithms/dominance.py
graphdict/algorithms/dominating.py
graphdict/algorithms/efficiency_measures.py
graphdict/algorithms/euler.py
graphdict/algorithms/graph_hashing.py
graphdict/algorithms/graphical.py
graphdict/algorithms/hierarchy.py
graphdict/algorithms/hybrid.py
graphdict/algorithms/isolate.py
graphdict/algorithms/link_prediction.py
graphdict/algorithms/lowest_common_ancestors.py
graphdict/algorithms/matching.py
graphdict/algorithms/mis.py
graphdict/algorithms/moral.py
graphdict/algorithms/non_randomness.py
graphdict/algorithms/planar_drawing.py
graphdict/algorithms/planarity.py
graphdict/algorithms/reciprocity.py
graphdict/algorithms/regular.py
graphdict/algorithms/richclub.py
graphdict/algorithms/similarity.py
graphdict/algorithms/simple_paths.py
graphdict/algorithms/smallworld.py
graphdict/algorithms/smetric.py
graphdict/algorithms/sparsifiers.py
graphdict/algorithms/structuralholes.py
graphdict/algorithms/summarization.py
graphdict/algorithms/swap.py
graphdict/algorithms/threshold.py
graphdict/algorithms/tournament.py
graphdict/algorithms/triads.py
graphdict/algorithms/vitality.py
graphdict/algorithms/voronoi.py
graphdict/algorithms/wiener.py
graphdict/algorithms/approximation/__init__.py
graphdict/algorithms/approximation/clique.py
graphdict-3.4.14.dist-info/licenses/LICENSE.txt
graphdict-3.4.14.dist-info/METADATA
graphdict-3.4.14.dist-info/WHEEL
graphdict-3.4.14.dist-info/top_level.txt
graphdict-3.4.14.dist-info/RECORD
