Metadata-Version: 2.4
Name: graphdict
Version: 3.4.14
Summary: Python package for creating and manipulating graphs and networks
Home-page: https://networkx.org/
Author: John Smith
Author-email: johnsmithdev92@gmail.com
Maintainer: Graphdict Developers
Maintainer-email: graphdict-discuss@googlegroups.com
Project-URL: Bug Tracker, https://github.com/taylortech75/graphdict/issues
Project-URL: Documentation, https://networkx.org/documentation/stable/
Project-URL: Source Code, https://github.com/taylortech75/graphdict
Keywords: Networks,Graph Theory,Mathematics,network,graph,discrete mathematics,math
Platform: Linux
Platform: Mac OSX
Platform: Windows
Platform: Unix
Classifier: Development Status :: 5 - Production/Stable
Classifier: Intended Audience :: Developers
Classifier: Intended Audience :: Science/Research
Classifier: License :: OSI Approved :: BSD License
Classifier: Operating System :: OS Independent
Classifier: Programming Language :: Python :: 3
Classifier: Programming Language :: Python :: 3.7
Classifier: Programming Language :: Python :: 3.8
Classifier: Programming Language :: Python :: 3.9
Classifier: Programming Language :: Python :: 3.10
Classifier: Programming Language :: Python :: 3.11
Classifier: Programming Language :: Python :: 3.12
Classifier: Programming Language :: Python :: 3.13
Classifier: Programming Language :: Python :: 3 :: Only
Classifier: Topic :: Software Development :: Libraries :: Python Modules
Classifier: Topic :: Scientific/Engineering :: Bio-Informatics
Classifier: Topic :: Scientific/Engineering :: Information Analysis
Classifier: Topic :: Scientific/Engineering :: Mathematics
Classifier: Topic :: Scientific/Engineering :: Physics
Requires-Python: >=3.7
License-File: LICENSE.txt
Provides-Extra: default
Requires-Dist: numpy>=1.19; extra == "default"
Requires-Dist: scipy!=1.6.1,>=1.5; extra == "default"
Requires-Dist: matplotlib>=3.3; extra == "default"
Requires-Dist: pandas>=1.1; extra == "default"
Provides-Extra: developer
Requires-Dist: black==21.5b1; extra == "developer"
Requires-Dist: pre-commit>=2.12; extra == "developer"
Provides-Extra: doc
Requires-Dist: sphinx~=4.0; extra == "doc"
Requires-Dist: pydata-sphinx-theme~=0.6; extra == "doc"
Requires-Dist: sphinx-gallery~=0.9; extra == "doc"
Requires-Dist: numpydoc>=1.1; extra == "doc"
Requires-Dist: pillow>=8.2; extra == "doc"
Requires-Dist: nb2plots>=0.6; extra == "doc"
Requires-Dist: texext>=0.6.6; extra == "doc"
Provides-Extra: extra
Requires-Dist: lxml>=4.5; extra == "extra"
Requires-Dist: pygraphviz>=1.7; extra == "extra"
Requires-Dist: pydot>=1.4.1; extra == "extra"
Provides-Extra: test
Requires-Dist: pytest>=6.2; extra == "test"
Requires-Dist: pytest-cov>=2.12; extra == "test"
Requires-Dist: codecov>=2.1; extra == "test"
Dynamic: author
Dynamic: author-email
Dynamic: classifier
Dynamic: description
Dynamic: home-page
Dynamic: keywords
Dynamic: license-file
Dynamic: maintainer
Dynamic: maintainer-email
Dynamic: platform
Dynamic: project-url
Dynamic: provides-extra
Dynamic: requires-python
Dynamic: summary
